dazel.py
dazel-0.0.43.dist-info/licenses/LICENSE
dazel-0.0.43.dist-info/METADATA
dazel-0.0.43.dist-info/WHEEL
dazel-0.0.43.dist-info/entry_points.txt
dazel-0.0.43.dist-info/top_level.txt
dazel-0.0.43.dist-info/RECORD
